mcp_sse_fetch_weather/__init__.py
mcp_sse_fetch_weather/__main__.py
mcp_sse_fetch_weather/server.py
mcp_sse_weather-0.0.3.dist-info/METADATA
mcp_sse_weather-0.0.3.dist-info/WHEEL
mcp_sse_weather-0.0.3.dist-info/entry_points.txt
mcp_sse_weather-0.0.3.dist-info/top_level.txt
mcp_sse_weather-0.0.3.dist-info/RECORD
