Metadata-Version: 2.4
Name: mcp-sse-weather
Version: 0.0.3
Summary: 输入OpenWeather-API-KEY，获取天气信息。
Requires-Python: >=3.10
Requires-Dist: httpx>=0.28.1
Requires-Dist: mcp>=1.13.1
